gad/__init__.py
gad/cli.py
gad/formats.py
mun_feas_ga_data-0.3.1.dist-info/LICENSE
mun_feas_ga_data-0.3.1.dist-info/METADATA
mun_feas_ga_data-0.3.1.dist-info/WHEEL
mun_feas_ga_data-0.3.1.dist-info/entry_points.txt
mun_feas_ga_data-0.3.1.dist-info/RECORD
