Metadata-Version: 2.3
Name: mun-feas-ga-data
Version: 0.3.1
Summary: Graduate Attribute (GA) data tools for Memorial's Faculty of Engineering and Applied Science
Author: Jonathan Anderson
Author-email: jonathan.anderson@mun.ca
Requires-Python: >=3.10
Classifier: Programming Language :: Python :: 3
Classifier: Programming Language :: Python :: 3.10
Classifier: Programming Language :: Python :: 3.11
Classifier: Programming Language :: Python :: 3.12
Classifier: Programming Language :: Python :: 3.13
Requires-Dist: click (>=8.3.0,<9.0.0)
Requires-Dist: openpyxl (>=3.1.5,<4.0.0)
Requires-Dist: pandas (>=2.3.3,<3.0.0)
Requires-Dist: seaborn (>=0.13.2,<0.14.0)
